topsis_python/topsis.py
topsis_101703192_girish_1.0.0-1.0.0.dist-info/LICENSE
topsis_101703192_girish_1.0.0-1.0.0.dist-info/METADATA
topsis_101703192_girish_1.0.0-1.0.0.dist-info/WHEEL
topsis_101703192_girish_1.0.0-1.0.0.dist-info/entry_points.txt
topsis_101703192_girish_1.0.0-1.0.0.dist-info/top_level.txt
topsis_101703192_girish_1.0.0-1.0.0.dist-info/RECORD
