Metadata-Version: 2.1
Name: topsis-101703192-girish-1.0.0
Version: 1.0.0
Summary: A Python package implementing TOPSIS technique.
Home-page: UNKNOWN
Author: Girish Julka
Author-email: gjulka_be17@thapar.edu
License: MIT
Platform: UNKNOWN
Classifier: License :: OSI Approved :: MIT License
Classifier: Programming Language :: Python :: 3
Classifier: Programming Language :: Python :: 3.7
Requires-Dist: scipy
Requires-Dist: tabulate
Requires-Dist: numpy
Requires-Dist: pandas
